[
  {
    "name": "Стулья",
    "description": "Отличные стулья для Вас",
    "created": "2021-09-13T20:36:22.146",
    "updated": "2021-09-13T20:42:04.938",
    "is_active": true
  },
  {
    "name": "Лампы",
    "description": "Отличные лампы для Вас",
    "created": "2021-09-13T20:36:22.152",
    "updated": "2021-09-13T20:41:43.791",
    "is_active": true
  },
  {
    "name": "Прочее",
    "description": "Может быть для Вас полезным",
    "created": "2021-09-13T20:36:22.157",
    "updated": "2021-09-13T20:47:39.927",
    "is_active": true
  }
]
